<annotation>
	<folder>JPEGImages</folder>
	<filename>9210739293_2b0e0d991e_k.jpg</filename>
	<path>E:\yolov5-6.0\VOCdevkit\VOC2007\JPEGImages\9210739293_2b0e0d991e_k.jpg</path>
	<source>
		<database>Unknown</database>
	</source>
	<size>
		<width>1365</width>
		<height>2048</height>
		<depth>3</depth>
	</size>
	<segmented>0</segmented>
	<object>
		<name>ballon</name>
		<pose>Unspecified</pose>
		<truncated>0</truncated>
		<difficult>0</difficult>
		<bndbox>
			<xmin>969</xmin>
			<ymin>523</ymin>
			<xmax>1216</xmax>
			<ymax>788</ymax>
		</bndbox>
	</object>
	<object>
		<name>person</name>
		<pose>Unspecified</pose>
		<truncated>0</truncated>
		<difficult>0</difficult>
		<bndbox>
			<xmin>263</xmin>
			<ymin>114</ymin>
			<xmax>907</xmax>
			<ymax>2012</ymax>
		</bndbox>
	</object>
	<object>
		<name>person</name>
		<pose>Unspecified</pose>
		<truncated>1</truncated>
		<difficult>0</difficult>
		<bndbox>
			<xmin>1143</xmin>
			<ymin>1097</ymin>
			<xmax>1365</xmax>
			<ymax>2048</ymax>
		</bndbox>
	</object>
	<object>
		<name>car</name>
		<pose>Unspecified</pose>
		<truncated>0</truncated>
		<difficult>0</difficult>
		<bndbox>
			<xmin>3</xmin>
			<ymin>614</ymin>
			<xmax>987</xmax>
			<ymax>1674</ymax>
		</bndbox>
	</object>
	<object>
		<name>car</name>
		<pose>Unspecified</pose>
		<truncated>0</truncated>
		<difficult>0</difficult>
		<bndbox>
			<xmin>716</xmin>
			<ymin>810</ymin>
			<xmax>1229</xmax>
			<ymax>1161</ymax>
		</bndbox>
	</object>
</annotation>
